mach4/__init__.py
mach4/debug.py
mach4/pipeline.py
mach4/security/__init__.py
mach4/security/event.py
mach4/security/generator.py
mach4/security/index.py
mach4/utils/__init__.py
mach4/utils/captcha.py
mach4/utils/error.py
mach4/utils/refresh.py
mach4/utils/response.py
mach4/utils/text.py
mach4-0.2.0.dist-info/LICENSE
mach4-0.2.0.dist-info/METADATA
mach4-0.2.0.dist-info/NOTICE
mach4-0.2.0.dist-info/WHEEL
mach4-0.2.0.dist-info/top_level.txt
mach4-0.2.0.dist-info/RECORD
