Metadata-Version: 2.1
Name: mach4
Version: 0.2.0
Summary: Mach4 is a Python3 API framework based on Flask. 
Home-page: https://github.com/alph4ice/Mach4
Author: Cyriaque Perier
License: UNKNOWN
Platform: UNKNOWN
Classifier: Programming Language :: Python :: 3
Classifier: License :: OSI Approved :: Apache Software License
Classifier: Operating System :: OS Independent
Requires-Python: >=3.6
License-File: LICENSE
License-File: NOTICE
Requires-Dist: PyJWT
Requires-Dist: Flask
